privjail/__init__.py
privjail/distance.py
privjail/mechanism.py
privjail/prisoner.py
privjail/provenance.py
privjail/util.py
privjail/egrpc/__init__.py
privjail/egrpc/compiler.py
privjail/egrpc/decorator.py
privjail/egrpc/entry_point.py
privjail/egrpc/grpc_interface.py
privjail/egrpc/instance_ref.py
privjail/egrpc/names.py
privjail/egrpc/proto_interface.py
privjail/egrpc/util.py
privjail/pandas/__init__.py
privjail/pandas/dataframe.py
privjail/pandas/domain.py
privjail/pandas/functions.py
privjail/pandas/groupby.py
privjail/pandas/series.py
privjail/pandas/util.py
privjail-0.0.3.dist-info/METADATA
privjail-0.0.3.dist-info/WHEEL
privjail-0.0.3.dist-info/licenses/LICENSE
privjail-0.0.3.dist-info/RECORD
