Metadata-Version: 2.4
Name: privjail
Version: 0.0.3
Summary: Enforcing differential privacy in Python
License-File: LICENSE
Requires-Python: >=3.11
Requires-Dist: grpcio-tools>=1.69.0
Requires-Dist: grpcio>=1.69.0
Requires-Dist: multimethod
Requires-Dist: numpy>=2.1.3
Requires-Dist: pandas>=2.2.3
Requires-Dist: sympy>=1.13.3
